rest_solace/__init__.py
rest_solace/consumer.py
rest_solace/exceptions.py
rest_solace/http_client.py
rest_solace/manager.py
rest_solace/messaging_schema.json
rest_solace/publisher.py
rest_solace-0.3.1.dist-info/LICENSE.txt
rest_solace-0.3.1.dist-info/METADATA
rest_solace-0.3.1.dist-info/NOTICE.txt
rest_solace-0.3.1.dist-info/WHEEL
rest_solace-0.3.1.dist-info/top_level.txt
rest_solace-0.3.1.dist-info/RECORD
