Metadata-Version: 2.1
Name: rest-solace
Version: 0.3.1
Summary: REST API library for Solace Message Broker. Publish, Consume, & Manage!!
Author-email: Skyler Guha <skylerguha@gmail.com>
Maintainer-email: Skyler Guha <skylerguha@gmail.com>
License: apache 2.0
Project-URL: pypi, https://pypi.org/project/rest-solace/
Project-URL: documentation, https://github.com/skyler-guha/rest-solace/blob/master/docs/index.rst
Project-URL: repository, https://github.com/skyler-guha/rest-solace
Keywords: solace,rest,REST API,rest-solace,rest_solace,rest solace,python,pythonic
Classifier: Development Status :: 4 - Beta
Classifier: Programming Language :: Python :: 3
Classifier: License :: OSI Approved :: Apache Software License
Classifier: Intended Audience :: Developers
Requires-Python: >=3.8
License-File: LICENSE.txt
License-File: NOTICE.txt
Requires-Dist: requests >=2.30.0
Requires-Dist: aiohttp >=3.9.5
Requires-Dist: jsonschema >=4.23.0
